{
  "app_id": 115933,
  "title": "Frete Click",
  "slug": "frete-click",
  "type": "external",
  "state": "active",
  "authentication": true,
  "modules": {
    "calculate_shipping": {
      "enabled": true,
      "endpoint": "https://us-central1-ecom-freteclick.cloudfunctions.net/app/ecom/modules/calculate-shipping"
    }
  },
  "auth_scope": {
    "stores/me": [
      "GET"
    ],
    "procedures": [
      "POST"
    ],
    "products": [],
    "brands": [],
    "categories": [],
    "customers": [],
    "orders": [
      "GET",
      "PATCH"
    ],
    "carts": [],
    "orders/fulfillments": [
      "POST"
    ],
    "orders/payments_history": [],
    "products/quantity": [],
    "products/variations/quantity": [],
    "products/price": [],
    "products/variations/price": []
  },
  "admin_settings": {
    "zip": {
      "schema": {
        "type": "string",
        "maxLength": 9,
        "pattern": "^[0-9]{5}-?[0-9]{3}$",
        "title": "CEP de origem"
      },
      "hide": true
    },
    "api_key": {
      "schema": {
        "type": "string",
        "maxLength": 600,
        "title": "Api Key",
        "description": "Solicite Api Key para Frete Click"
      },
      "hide": true
    },
    "best_quotation": {
      "schema": {
        "type": "boolean",
        "default": true,
        "title": "Retonar melhor cotação",
        "hint": "Retornar a cotação de melhor custo e prazo apenas, com o intuito de não confundir clientes"
      },
      "hide": true
    },
    "send_tag_status": {
      "schema": {
        "type": "boolean",
        "default": true,
        "title": "Enviar pedido pra frete click"
      },
      "hide": true
    },
    "from": {
      "schema": {
        "type": "object",
        "title": "Endereço do remetente",
        "description": "Configure endereço de remetente para cálculo.",
        "properties": {
          "street": {
            "type": "string",
            "maxLength": 100,
            "title": "Rua"
          },
          "borough": {
            "type": "string",
            "maxLength": 100,
            "title": "Bairro"
          },
          "number": {
            "type": "number",
            "maxLength": 100,
            "title": "Número"
          },
          "complement": {
            "type": "number",
            "maxLength": 100,
            "title": "Complemento"
          },
          "city": {
            "type": "string",
            "maxLength": 100,
            "title": "Cidade de Origem"
          },
          "province_code": {
            "type": "string",
            "title": "Sigla do Estado de Origem",
            "enum": [
              "AC",
              "AL",
              "AP",
              "AM",
              "BA",
              "CE",
              "DF",
              "ES",
              "GO",
              "MA",
              "MT",
              "MS",
              "MG",
              "PA",
              "PB",
              "PR",
              "PE",
              "PI",
              "RR",
              "RO",
              "RJ",
              "RS",
              "RN",
              "SC",
              "SP",
              "SE",
              "TO"
            ]
          },
          "country": {
            "type": "string",
            "maxLength": 100,
            "title": "País de Origem"
          }
        }
      },
      "hide": true
    },
    "posting_deadline": {
      "schema": {
        "title": "Prazo de postagem",
        "type": "object",
        "required": [
          "days"
        ],
        "additionalProperties": false,
        "properties": {
          "days": {
            "type": "integer",
            "minimum": 0,
            "maximum": 999999,
            "title": "Número de dias",
            "description": "Dias de prazo para postar os produtos após a compra"
          },
          "working_days": {
            "type": "boolean",
            "default": true,
            "title": "Dias úteis"
          },
          "after_approval": {
            "type": "boolean",
            "default": true,
            "title": "Após aprovação do pagamento"
          }
        }
      },
      "hide": false
    },
    "additional_price": {
      "schema": {
        "type": "number",
        "minimum": -999999,
        "maximum": 999999,
        "title": "Custo adicional",
        "description": "Valor a adicionar (negativo para descontar) no frete calculado em todas regras"
      },
      "hide": false
    },
    "services": {
      "schema": {
        "title": "Rótulo dos Serviços",
        "description": "Para alterar o nome de exibição de algum serviço basta infomar o código do serviço e um novo rótulo de exibição.",
        "type": "array",
        "maxItems": 6,
        "items": {
          "title": "Serviço de entrega",
          "type": "object",
          "required": [
            "service_name",
            "label"
          ],
          "properties": {
            "service_name": {
              "type": "string",
              "title": "Serviço",
              "description": "Nome oficial do serviço na transportadora"
            },
            "label": {
              "type": "string",
              "maxLength": 50,
              "title": "Rótulo",
              "description": "Nome do serviço exibido aos clientes"
            }
          }
        }
      },
      "hide": true
    },
    "free_shipping_rules": {
      "schema": {
        "title": "Regras de frete grátis",
        "type": "array",
        "maxItems": 300,
        "items": {
          "title": "Regra de frete grátis",
          "type": "object",
          "minProperties": 1,
          "properties": {
            "zip_range": {
              "title": "Faixa de CEP",
              "type": "object",
              "required": [
                "min",
                "max"
              ],
              "properties": {
                "min": {
                  "type": "integer",
                  "minimum": 10000,
                  "maximum": 999999999,
                  "title": "CEP inicial"
                },
                "max": {
                  "type": "integer",
                  "minimum": 10000,
                  "maximum": 999999999,
                  "title": "CEP final"
                }
              }
            },
            "min_amount": {
              "type": "number",
              "minimum": 1,
              "maximum": 999999999,
              "title": "Valor mínimo da compra"
            },
            "product_ids": {
              "title": "Lista de produtos",
              "description": "Se preenchido, o desconto só será válido se um dos produtos estiver no carrinho",
              "type": "array",
              "items": {
                "type": "string",
                "pattern": "^[a-f0-9]{24}$",
                "title": "ID do produto"
              }
            },
            "all_product_ids": {
              "type": "boolean",
              "title": "Checar todos os produtos",
              "description": "Se ativo, a regra será disponibilizada apenas se todos os itens do carrinho estiverem na lista de produtos selecionados"
            }
          }
        }
      },
      "hide": false
    },
    "shipping_rules": {
      "schema": {
        "title": "Regras de envio",
        "description": "Aplicar descontos/adicionais condiciAtivar regiões",
        "type": "array",
        "maxItems": 300,
        "items": {
          "title": "Regra de envio",
          "type": "object",
          "minProperties": 1,
          "properties": {
            "service_name": {
              "type": "string",
              "title": "Nome do serviço"
            },
            "zip_range": {
              "title": "Faixa de CEP",
              "type": "object",
              "required": [
                "min",
                "max"
              ],
              "properties": {
                "min": {
                  "type": "integer",
                  "minimum": 10000,
                  "maximum": 999999999,
                  "title": "CEP inicial"
                },
                "max": {
                  "type": "integer",
                  "minimum": 10000,
                  "maximum": 999999999,
                  "title": "CEP final"
                }
              }
            },
            "min_amount": {
              "type": "number",
              "minimum": 1,
              "maximum": 999999999,
              "title": "Valor mínimo da compra"
            },
            "discount": {
              "title": "Desconto",
              "type": "object",
              "required": [
                "value"
              ],
              "properties": {
                "percentage": {
                  "type": "boolean",
                  "default": false,
                  "title": "Desconto percentual"
                },
                "value": {
                  "type": "number",
                  "minimum": -99999999,
                  "maximum": 99999999,
                  "title": "Valor do desconto",
                  "description": "Valor percentual/fixo do desconto ou acréscimo (negativo)"
                }
              }
            }
          }
        }
      },
      "hide": false
    },
    "disable_shipping": {
      "schema": {
        "type": "string",
        "maxLength": 100,
        "title": "Remover transportadoras",
        "description": "Insira a lista de IDs separados por vírgula de transportadoras que serão removidas do cálculo"
      },
      "hide": true
    }
  },
  "auth_callback_uri": "https://us-central1-ecom-freteclick.cloudfunctions.net/app/ecom/auth-callback",
  "version": "1.0.0"
}